{
    "act": "init",
    "data":
    {
        "number": "942586",
        "running": "0",
        "room_users": [
        {
            "user_id": "530029",
            "nickname": "infi000",
            "path": "https:\/\/wx.qlogo.cn\/mmopen\/vi_32\/ajNVdqHZLLAp6GGaTqpibLUzRWbMFldywn1QagzbWOppxzkL4cG42C2lyI0H6Ye67EXtdmIAo4YajoKWnU8XL9Q\/64",
            "online": "1",
            "is_join": "0",
            "value": "0",
            "position": "2"
        },
        {
            "user_id": "530067",
            "nickname": "\ud83d\ude18tvmceshi\ud83e\udd11",
            "path": "https:\/\/wx.qlogo.cn\/mmopen\/vi_32\/Q0j4TwGTfTKoIFN9ondgVIkKdXslcKP5f4RicoQnv41WkpYaic6bEjoCYtD9bFOg5hge3Ced0KKQia7RIbuZucRlw\/64",
            "online": "1",
            "is_join": "0",
            "value": "0",
            "position": "1"
        }],
        "max_matches": "10",
        "cur_match": "0",
        "end_points": "2",
        "chip_rule": "1",
        "upper_limit": "500",
        "max_chip": "20"
    }
}
{
    "act": "gameRunning",
    "data":
    {
        "running": "0",
        "cur_match": "0",
        "users": [
            ["530067", "1", "0"],
            ["530029", "1", "0"]
        ]
    }
}
{
    "act": "init",
    "data":
    {
        "number": "942586",
        "running": "0",
        "room_users": [
        {
            "user_id": "530029",
            "nickname": "infi000",
            "path": "https:\/\/wx.qlogo.cn\/mmopen\/vi_32\/ajNVdqHZLLAp6GGaTqpibLUzRWbMFldywn1QagzbWOppxzkL4cG42C2lyI0H6Ye67EXtdmIAo4YajoKWnU8XL9Q\/64",
            "online": "1",
            "is_join": "0",
            "value": "0",
            "position": "2"
        },
        {
            "user_id": "530067",
            "nickname": "\ud83d\ude18tvmceshi\ud83e\udd11",
            "path": "https:\/\/wx.qlogo.cn\/mmopen\/vi_32\/Q0j4TwGTfTKoIFN9ondgVIkKdXslcKP5f4RicoQnv41WkpYaic6bEjoCYtD9bFOg5hge3Ced0KKQia7RIbuZucRlw\/64",
            "online": "1",
            "is_join": "0",
            "value": "0",
            "position": "1"
        }],
        "max_matches": "10",
        "cur_match": "0",
        "end_points": "2",
        "chip_rule": "1",
        "upper_limit": "500",
        "max_chip": "20"
    }
}
{
    "data": "",
    "act": "ready"
}
{
    "act": "ready",
    "data": "530029"
}
{
    "act": "ready",
    "data": "530067"
}
{
    "act": "start",
    "data":
    {
        "cur_match": "1",
        "user_list": [
        {
            "user_id": "530029",
            "value": "-2"
        },
        {
            "user_id": "530067",
            "value": "-2"
        }],
        "total_chip": "4",
        "end_points": "2"
    }
}
{
    "act": "chipInStart",
    "data":
    {
        "chipList": ["2", "4", "8", "10"],
        "is_compare": "0",
        "max_chip": "2",
        "is_showdown": "0",
        "user_id": "530029",
        "compare_button": "1",
        "round": "0"
    }
}
{
    "act": "userTime",
    "data":
    {
        "user_id": "530029",
        "s": "15"
    }
}
{
    "act": "userTime",
    "data":
    {
        "user_id": "530029",
        "s": "14"
    }
}
{
    "act": "userTime",
    "data":
    {
        "user_id": "530029",
        "s": "13"
    }
}
{
    "data": "",
    "act": "lookCards"
}
{
    "act": "updateChipIn",
    "data":
    {
        "chipList": ["4", "8", "16", "20"],
        "max_chip": "4",
        "current_chip": "0"
    }
}
{
    "act": "lookCards",
    "data":
    {
        "round": "0",
        "cards": [
        {
            "color": "1",
            "value": "4"
        },
        {
            "color": "0",
            "value": "4"
        },
        {
            "color": "1",
            "value": "12"
        }],
        "cards_type": "1",
        "sex": "1"
    }
}
{
    "act": "userTime",
    "data":
    {
        "user_id": "530029",
        "s": "12"
    }
}
{
    "act": "userTime",
    "data":
    {
        "user_id": "530029",
        "s": "11"
    }
}
{
    "act": "userTime",
    "data":
    {
        "user_id": "530029",
        "s": "10"
    }
}
{
    "data": "16",
    "act": "chipIn"
}
{
    "act": "chipIn",
    "data":
    {
        "user_id": "530029",
        "chip": "16",
        "total_chip": "20",
        "value": "-18",
        "sex": "1",
        "round": "0"
    }
}
{
    "act": "userTime",
    "data":
    {
        "user_id": "530067",
        "s": "15"
    }
}
{
    "act": "userTime",
    "data":
    {
        "user_id": "530067",
        "s": "14"
    }
}
{
    "act": "showfanpaiTips",
    "data":
    {
        "round": "0",
        "user_id": "530067",
        "sex": "1"
    }
}
{
    "act": "userTime",
    "data":
    {
        "user_id": "530067",
        "s": "13"
    }
}
{
    "act": "userTime",
    "data":
    {
        "user_id": "530067",
        "s": "12"
    }
}
{
    "act": "chipIn",
    "data":
    {
        "user_id": "530067",
        "chip": "16",
        "total_chip": "36",
        "value": "-18",
        "sex": "1",
        "round": "0"
    }
}
{
    "act": "chipInStart",
    "data":
    {
        "chipList": ["4", "8", "16", "20"],
        "is_compare": "1",
        "max_chip": "16",
        "is_showdown": "1",
        "user_id": "530029",
        "compare_button": "1",
        "round": "1"
    }
}
{
    "act": "userTime",
    "data":
    {
        "user_id": "530029",
        "s": "15"
    }
}
{
    "act": "userTime",
    "data":
    {
        "user_id": "530029",
        "s": "14"
    }
}
{
    "data": "",
    "act": "compareUsers"
}
{
    "act": "compareCardsChip",
    "data":
    {
        "user_id": "530029",
        "chip": "16",
        "total_chip": "52",
        "value": "-34"
    }
}
{
    "act": "cards",
    "data": [
    {
        "user_id": "530029",
        "win": "530029"
    },
    {
        "user_id": "530067",
        "lose": "530067",
        "cards_type": "0",
        "cards": [
        {
            "color": "3",
            "value": "14"
        },
        {
            "color": "2",
            "value": "5"
        },
        {
            "color": "0",
            "value": "3"
        }]
    }]
}
{
    "act": "compareCards",
    "data":
    {
        "win": "530029",
        "lose": ["530067"],
        "round": "1",
        "sex": "1"
    }
}
{
    "act": "settlement",
    "data":
    {
        "win": "530029",
        "winValue": "18"
    }
}
{
    "data": "",
    "act": "ready"
}
{
    "act": "ready",
    "data": "530029"
}
{
    "act": "ready",
    "data": "530067"
}
{
    "act": "start",
    "data":
    {
        "cur_match": "2",
        "user_list": [
        {
            "user_id": "530029",
            "value": "16"
        },
        {
            "user_id": "530067",
            "value": "-20"
        }],
        "total_chip": "4",
        "end_points": "2"
    }
}
{
    "act": "chipInStart",
    "data":
    {
        "chipList": ["2", "4", "8", "10"],
        "is_compare": "0",
        "max_chip": "2",
        "is_showdown": "0",
        "user_id": "530029",
        "compare_button": "1",
        "round": "0"
    }
}
{
    "act": "userTime",
    "data":
    {
        "user_id": "530029",
        "s": "15"
    }
}
{
    "act": "userTime",
    "data":
    {
        "user_id": "530029",
        "s": "14"
    }
}
{
    "data": "",
    "act": "discard"
}
{
    "act": "discard",
    "data":
    {
        "round": "0",
        "user_id": "530029",
        "sex": "1"
    }
}
{
    "act": "settlement",
    "data":
    {
        "win": "530067",
        "winValue": "-16"
    }
}
{
    "data": "",
    "act": "ready"
}
{
    "act": "ready",
    "data": "530029"
}
{
    "act": "ready",
    "data": "530067"
}
{
    "act": "start",
    "data":
    {
        "cur_match": "3",
        "user_list": [
        {
            "user_id": "530029",
            "value": "14"
        },
        {
            "user_id": "530067",
            "value": "-18"
        }],
        "total_chip": "4",
        "end_points": "2"
    }
}
{
    "act": "chipInStart",
    "data":
    {
        "chipList": ["2", "4", "8", "10"],
        "is_compare": "0",
        "max_chip": "2",
        "is_showdown": "0",
        "user_id": "530029",
        "compare_button": "1",
        "round": "0"
    }
}
{
    "act": "userTime",
    "data":
    {
        "user_id": "530029",
        "s": "15"
    }
}
{
    "act": "userTime",
    "data":
    {
        "user_id": "530029",
        "s": "14"
    }
}
{
    "data": "2",
    "act": "chipIn"
}
{
    "act": "chipIn",
    "data":
    {
        "user_id": "530029",
        "chip": "2",
        "total_chip": "6",
        "value": "12",
        "sex": "1",
        "round": "0"
    }
}
{
    "act": "userTime",
    "data":
    {
        "user_id": "530067",
        "s": "15"
    }
}
{
    "act": "chipIn",
    "data":
    {
        "user_id": "530067",
        "chip": "2",
        "total_chip": "8",
        "value": "-20",
        "sex": "1",
        "round": "0"
    }
}
{
    "act": "chipInStart",
    "data":
    {
        "chipList": ["2", "4", "8", "10"],
        "is_compare": "1",
        "max_chip": "2",
        "is_showdown": "0",
        "user_id": "530029",
        "compare_button": "1",
        "round": "1"
    }
}
{
    "act": "userTime",
    "data":
    {
        "user_id": "530029",
        "s": "15"
    }
}
{
    "data": "4",
    "act": "chipIn"
}
{
    "act": "chipIn",
    "data":
    {
        "user_id": "530029",
        "chip": "4",
        "total_chip": "12",
        "value": "8",
        "sex": "1",
        "round": "1"
    }
}
{
    "act": "userTime",
    "data":
    {
        "user_id": "530067",
        "s": "15"
    }
}
{
    "act": "showfanpaiTips",
    "data":
    {
        "round": "1",
        "user_id": "530067",
        "sex": "1"
    }
}
{
    "act": "userTime",
    "data":
    {
        "user_id": "530067",
        "s": "14"
    }
}
{
    "act": "compareCardsChip",
    "data":
    {
        "user_id": "530067",
        "chip": "8",
        "total_chip": "20",
        "value": "-28"
    }
}
{
    "act": "cards",
    "data": [
    {
        "user_id": "530067",
        "lose": "530067",
        "cards_type": "0",
        "cards": [
        {
            "color": "3",
            "value": "2"
        },
        {
            "color": "3",
            "value": "14"
        },
        {
            "color": "1",
            "value": "5"
        }]
    },
    {
        "user_id": "530029",
        "win": "530029",
        "cards_type": "1",
        "cards": [
        {
            "color": "2",
            "value": "14"
        },
        {
            "color": "2",
            "value": "2"
        },
        {
            "color": "0",
            "value": "2"
        }]
    }]
}
{
    "act": "compareCards",
    "data":
    {
        "win": "530029",
        "lose": ["530067"],
        "round": "1",
        "sex": "1"
    }
}
{
    "act": "settlement",
    "data":
    {
        "win": "530029",
        "winValue": "28"
    }
}
{
    "act": "playerleave",
    "data":
    {
        "user_id": "530067",
        "is_exist": "1"
    }
}
{
    "act": "playerjoin",
    "data":
    {
        "user_id": "530067",
        "nickname": "\ud83d\ude18tvmceshi\ud83e\udd11",
        "path": "https:\/\/wx.qlogo.cn\/mmopen\/vi_32\/Q0j4TwGTfTKoIFN9ondgVIkKdXslcKP5f4RicoQnv41WkpYaic6bEjoCYtD9bFOg5hge3Ced0KKQia7RIbuZucRlw\/64",
        "sex": "1",
        "position": "1"
    }
}